.gitattributes
.gitignore
LICENSE.txt
MANIFEST.in
Makefile
README.rst
create_codec_source.py
setup.py
cbmcodecs2/__init__.py
cbmcodecs2/petscii_c64en_lc.py
cbmcodecs2/petscii_c64en_uc.py
cbmcodecs2/petscii_vic1001jp_gr.py
cbmcodecs2/petscii_vic1001jp_kk.py
cbmcodecs2/petscii_vic20en_lc.py
cbmcodecs2/petscii_vic20en_uc.py
cbmcodecs2/screencode_c64_lc.py
cbmcodecs2/screencode_c64_uc.py
cbmcodecs2.egg-info/PKG-INFO
cbmcodecs2.egg-info/SOURCES.txt
cbmcodecs2.egg-info/dependency_links.txt
cbmcodecs2.egg-info/top_level.txt
mappings/pet_unicode.txt
mappings/petscii_c64en_lc.txt
mappings/petscii_c64en_uc.txt
mappings/petscii_vic1001jp_gr.txt
mappings/petscii_vic1001jp_kk.txt
mappings/petscii_vic20en_lc.txt
mappings/petscii_vic20en_uc.txt
mappings/screencode_c64_lc.txt
mappings/screencode_c64_uc.txt
tests/__init__.py
tests/codec_test.py