Metadata-Version: 2.1
Name: cbmcodecs2
Version: 1.3
Summary: Python codecs for CBM PETSCII and Screencode encodings
Home-page: https://github.com/irmen/cbmcodecs2
Author: Irmen de Jong
Author-email: irmen@razorvine.net
License: GPLv2
Platform: UNKNOWN
Classifier: Development Status :: 4 - Beta
Classifier: Intended Audience :: Developers
Classifier: License :: OSI Approved :: GNU General Public License v2 (GPLv2)
Classifier: Programming Language :: Python
Classifier: Programming Language :: Python :: 3
Classifier: Topic :: Software Development :: Libraries :: Python Modules
License-File: LICENSE.txt
